app/__init__.py
app/app_factory.py
app/logging/__init__.py
app/logging/log_config.py
routes/__init__.py
routes/healthcheck_route.py
routes/prediction_route.py
flask_gunicorn_docker-0.0.0.dist-info/METADATA
flask_gunicorn_docker-0.0.0.dist-info/WHEEL
flask_gunicorn_docker-0.0.0.dist-info/top_level.txt
flask_gunicorn_docker-0.0.0.dist-info/RECORD
